dj_link/Main.py
dj_link/__init__.py
dj_link/link_shortener.py
dj_link-0.1.1.dist-info/entry_points.txt
dj_link-0.1.1.dist-info/WHEEL
dj_link-0.1.1.dist-info/METADATA
dj_link-0.1.1.dist-info/RECORD
