Metadata-Version: 2.1
Name: dj-link
Version: 0.1.1
Summary: 
Author: dongjin2008
Author-email: 80329234+dongjin2008@users.noreply.github.com
Requires-Python: >=3.9,<4.0
Classifier: Programming Language :: Python :: 3
Classifier: Programming Language :: Python :: 3.9
Classifier: Programming Language :: Python :: 3.10
Classifier: Programming Language :: Python :: 3.11
Requires-Dist: pyshorteners (>=1.0.1,<2.0.0)
